Metadata-Version: 1.1
Name: py-aho-corasick
Version: 1.0.0
Summary: py-aho-corasick
Home-page: https://github.com/JanFan/py_aho_corasick
Author: JanFan
Author-email: guangyizhang.jan@gmail.com
License: MIT license
Keywords: py_aho_corasick
Platform: UNKNOWN
Classifier: Development Status :: 2 - Pre-Alpha
Classifier: Intended Audience :: Developers
Classifier: License :: OSI Approved :: MIT License
Classifier: Natural Language :: English
Classifier: Programming Language :: Python :: 2
Classifier: Programming Language :: Python :: 2.6
Classifier: Programming Language :: Python :: 2.7
Classifier: Programming Language :: Python :: 3
Classifier: Programming Language :: Python :: 3.3
Classifier: Programming Language :: Python :: 3.4
Classifier: Programming Language :: Python :: 3.5
